{
  "movie_results": [],
  "person_results": [
    {
      "id": 1892,
      "name": "Matt Damon",
      "original_name": "Matt Damon",
      "media_type": "person",
      "adult": false,
      "popularity": 11.936,
      "gender": 2,
      "known_for_department": "Acting",
      "profile_path": "/At3JgvaNeEN4Z4ESKlhhes85Xo3.jpg",
      "known_for": [
        {
          "backdrop_path": "/9pubUbDX3eKB6ZuKxbFgv4cBZrz.jpg",
          "id": 286217,
          "title": "The Martian",
          "original_title": "The Martian",
          "overview": "During a manned mission to Mars, Astronaut Mark Watney is presumed dead after a fierce storm and left behind by his crew. But Watney has survived and finds himself stranded and alone on the hostile planet. With only meager supplies, he must draw upon his ingenuity, wit and spirit to subsist and find a way to signal to Earth that he is alive.",
          "poster_path": "/3ndAx3weG6KDkJIRMCi5vXX6Dyb.jpg",
          "media_type": "movie",
          "adult": false,
          "original_language": "en",
          "genre_ids": [
            18,
            12,
            878
          ],
          "popularity": 11.4914,
          "release_date": "2015-09-30",
          "video": false,
          "vote_average": 7.688,
          "vote_count": 20151
        },
        {
          "backdrop_path": "/oLsts7ct0NVkdYpx5rZg10MG6zh.jpg",
          "id": 489,
          "title": "Good Will Hunting",
          "original_title": "Good Will Hunting",
          "overview": "Headstrong yet aimless, Will Hunting has a genius-level IQ but chooses to work as a janitor at MIT. When he secretly solves highly difficult graduate-level math problems, his talents are discovered by Professor Gerald Lambeau, who decides to help the misguided youth reach his potential. When Will is arrested for attacking a police officer, Professor Lambeau makes a deal to get leniency for him if he gets court-ordered therapy. Eventually, therapist Dr. Sean Maguire helps Will confront the demons that are holding him back.",
          "poster_path": "/z2FnLKpFi1HPO7BEJxdkv6hpJSU.jpg",
          "media_type": "movie",
          "adult": false,
          "original_language": "en",
          "genre_ids": [
            18
          ],
          "popularity": 13.6237,
          "release_date": "1997-12-05",
          "video": false,
          "vote_average": 8.158,
          "vote_count": 12799
        },
        {
          "backdrop_path": "/kJaRWmy1BGq3pHyE94LOTteiHer.jpg",
          "id": 2501,
          "title": "The Bourne Identity",
          "original_title": "The Bourne Identity",
          "overview": "Wounded to the brink of death and suffering from amnesia, Jason Bourne is rescued at sea by a fisherman. With nothing to go on but a Swiss bank account number, he starts to reconstruct his life, but finds that many people he encounters want him dead. However, Bourne realizes that he has the combat and mental skills of a world-class spy—but who does he work for?",
          "poster_path": "/aP8swke3gmowbkfZ6lmNidu0y9p.jpg",
          "media_type": "movie",
          "adult": false,
          "original_language": "en",
          "genre_ids": [
            28,
            18,
            9648,
            53
          ],
          "popularity": 8.1088,
          "release_date": "2002-06-14",
          "video": false,
          "vote_average": 7.468,
          "vote_count": 9489
        }
      ]
    }
  ],
  "tv_results": [],
  "tv_episode_results": [],
  "tv_season_results": []
}
