{
  "results": [
    {
      "id": 208453,
      "adult": false
    },
    {
      "id": 89490,
      "adult": false
    },
    {
      "id": 116753,
      "adult": false
    },
    {
      "id": 156350,
      "adult": false
    },
    {
      "id": 213761,
      "adult": false
    },
    {
      "id": 194831,
      "adult": false
    },
    {
      "id": 71790,
      "adult": false
    },
    {
      "id": 80713,
      "adult": false
    },
    {
      "id": 65355,
      "adult": false
    },
    {
      "id": 34663,
      "adult": false
    },
    {
      "id": 216394,
      "adult": false
    },
    {
      "id": 152504,
      "adult": false
    },
    {
      "id": 209377,
      "adult": false
    },
    {
      "id": 155773,
      "adult": false
    },
    {
      "id": 201887,
      "adult": false
    },
    {
      "id": 84667,
      "adult": false
    },
    {
      "id": 169582,
      "adult": false
    },
    {
      "id": 30981,
      "adult": false
    },
    {
      "id": 57243,
      "adult": false
    },
    {
      "id": 119051,
      "adult": false
    },
    {
      "id": 99778,
      "adult": false
    },
    {
      "id": 114473,
      "adult": false
    },
    {
      "id": 205308,
      "adult": false
    },
    {
      "id": 97372,
      "adult": true
    },
    {
      "id": 112486,
      "adult": false
    },
    {
      "id": 69306,
      "adult": false
    },
    {
      "id": 211088,
      "adult": false
    },
    {
      "id": 87362,
      "adult": false
    },
    {
      "id": 76669,
      "adult": false
    },
    {
      "id": 114068,
      "adult": false
    },
    {
      "id": 119272,
      "adult": false
    },
    {
      "id": 102420,
      "adult": false
    },
    {
      "id": 77400,
      "adult": false
    },
    {
      "id": 206385,
      "adult": false
    },
    {
      "id": 158293,
      "adult": false
    },
    {
      "id": 156517,
      "adult": false
    },
    {
      "id": 115577,
      "adult": false
    },
    {
      "id": 70882,
      "adult": false
    },
    {
      "id": 130685,
      "adult": false
    },
    {
      "id": 72844,
      "adult": false
    },
    {
      "id": 95011,
      "adult": false
    },
    {
      "id": 80286,
      "adult": false
    },
    {
      "id": 107314,
      "adult": false
    },
    {
      "id": 208938,
      "adult": false
    },
    {
      "id": 215101,
      "adult": false
    },
    {
      "id": 1447,
      "adult": false
    },
    {
      "id": 105114,
      "adult": false
    },
    {
      "id": 204390,
      "adult": false
    },
    {
      "id": 103580,
      "adult": false
    },
    {
      "id": 61592,
      "adult": false
    },
    {
      "id": 118359,
      "adult": false
    },
    {
      "id": 215217,
      "adult": true
    },
    {
      "id": 115678,
      "adult": false
    },
    {
      "id": 214668,
      "adult": false
    },
    {
      "id": 210734,
      "adult": false
    },
    {
      "id": 216398,
      "adult": false
    },
    {
      "id": 89108,
      "adult": false
    },
    {
      "id": 100226,
      "adult": false
    },
    {
      "id": 60572,
      "adult": false
    },
    {
      "id": 197593,
      "adult": false
    },
    {
      "id": 216403,
      "adult": false
    },
    {
      "id": 45957,
      "adult": false
    },
    {
      "id": 97868,
      "adult": true
    },
    {
      "id": 65844,
      "adult": false
    },
    {
      "id": 36697,
      "adult": false
    },
    {
      "id": 214669,
      "adult": false
    },
    {
      "id": 39068,
      "adult": false
    },
    {
      "id": 214454,
      "adult": false
    },
    {
      "id": 7389,
      "adult": false
    },
    {
      "id": 202837,
      "adult": false
    },
    {
      "id": 205783,
      "adult": false
    },
    {
      "id": 153223,
      "adult": false
    },
    {
      "id": 46786,
      "adult": false
    },
    {
      "id": 75896,
      "adult": false
    },
    {
      "id": 94623,
      "adult": false
    },
    {
      "id": 52890,
      "adult": false
    },
    {
      "id": 30984,
      "adult": false
    },
    {
      "id": 210942,
      "adult": false
    },
    {
      "id": 96954,
      "adult": false
    },
    {
      "id": 92600,
      "adult": false
    },
    {
      "id": 58688,
      "adult": false
    },
    {
      "id": 2093,
      "adult": false
    },
    {
      "id": 215588,
      "adult": false
    },
    {
      "id": 14471,
      "adult": false
    },
    {
      "id": 61662,
      "adult": false
    },
    {
      "id": 216418,
      "adult": false
    },
    {
      "id": 206112,
      "adult": false
    },
    {
      "id": 78191,
      "adult": false
    },
    {
      "id": 216400,
      "adult": false
    },
    {
      "id": 1489,
      "adult": false
    },
    {
      "id": 38175,
      "adult": false
    },
    {
      "id": 64061,
      "adult": false
    },
    {
      "id": 216408,
      "adult": false
    },
    {
      "id": 70862,
      "adult": false
    },
    {
      "id": 70713,
      "adult": false
    },
    {
      "id": 82728,
      "adult": false
    },
    {
      "id": 62745,
      "adult": false
    },
    {
      "id": 7166,
      "adult": false
    },
    {
      "id": 152647,
      "adult": false
    },
    {
      "id": 216337,
      "adult": false
    },
    {
      "id": 210394,
      "adult": false
    },
    {
      "id": 104868,
      "adult": false
    },
    {
      "id": 135334,
      "adult": false
    },
    {
      "id": 215871,
      "adult": false
    },
    {
      "id": 117534,
      "adult": false
    },
    {
      "id": 203504,
      "adult": false
    },
    {
      "id": 60059,
      "adult": false
    },
    {
      "id": 99626,
      "adult": false
    },
    {
      "id": 214509,
      "adult": false
    },
    {
      "id": 92628,
      "adult": false
    },
    {
      "id": 216399,
      "adult": false
    },
    {
      "id": 549,
      "adult": false
    },
    {
      "id": 97421,
      "adult": false
    },
    {
      "id": 213852,
      "adult": false
    },
    {
      "id": 94199,
      "adult": false
    },
    {
      "id": 131041,
      "adult": false
    },
    {
      "id": 139798,
      "adult": false
    },
    {
      "id": 94372,
      "adult": false
    },
    {
      "id": 213728,
      "adult": false
    },
    {
      "id": 4384,
      "adult": false
    },
    {
      "id": 216424,
      "adult": false
    },
    {
      "id": 213169,
      "adult": false
    },
    {
      "id": 211829,
      "adult": false
    },
    {
      "id": 9463,
      "adult": false
    },
    {
      "id": 153554,
      "adult": false
    },
    {
      "id": 206028,
      "adult": false
    },
    {
      "id": 58314,
      "adult": false
    },
    {
      "id": 46437,
      "adult": false
    },
    {
      "id": 34744,
      "adult": false
    },
    {
      "id": 99071,
      "adult": false
    },
    {
      "id": 76092,
      "adult": false
    },
    {
      "id": 135271,
      "adult": false
    },
    {
      "id": 114410,
      "adult": false
    },
    {
      "id": 212930,
      "adult": false
    },
    {
      "id": 215740,
      "adult": false
    },
    {
      "id": 121702,
      "adult": false
    },
    {
      "id": 95676,
      "adult": false
    },
    {
      "id": 35260,
      "adult": false
    },
    {
      "id": 114868,
      "adult": false
    },
    {
      "id": 69773,
      "adult": false
    },
    {
      "id": 12519,
      "adult": false
    },
    {
      "id": 134843,
      "adult": false
    },
    {
      "id": 64292,
      "adult": false
    },
    {
      "id": 67842,
      "adult": false
    },
    {
      "id": 216230,
      "adult": false
    },
    {
      "id": 95341,
      "adult": false
    },
    {
      "id": 88,
      "adult": false
    },
    {
      "id": 97852,
      "adult": false
    },
    {
      "id": 30801,
      "adult": false
    },
    {
      "id": 36622,
      "adult": false
    },
    {
      "id": 125156,
      "adult": false
    },
    {
      "id": 13893,
      "adult": false
    },
    {
      "id": 1668,
      "adult": false
    },
    {
      "id": 113627,
      "adult": false
    },
    {
      "id": 153525,
      "adult": false
    },
    {
      "id": 22055,
      "adult": false
    },
    {
      "id": 208569,
      "adult": false
    },
    {
      "id": 202099,
      "adult": false
    },
    {
      "id": 65930,
      "adult": false
    },
    {
      "id": 214328,
      "adult": false
    },
    {
      "id": 16054,
      "adult": false
    },
    {
      "id": 197067,
      "adult": false
    },
    {
      "id": 94664,
      "adult": false
    },
    {
      "id": 210231,
      "adult": false
    },
    {
      "id": 194511,
      "adult": false
    },
    {
      "id": 106621,
      "adult": false
    },
    {
      "id": 104395,
      "adult": false
    },
    {
      "id": 202909,
      "adult": true
    },
    {
      "id": 107293,
      "adult": false
    },
    {
      "id": 135207,
      "adult": false
    },
    {
      "id": 60833,
      "adult": false
    },
    {
      "id": 203384,
      "adult": false
    },
    {
      "id": 197242,
      "adult": false
    },
    {
      "id": 216404,
      "adult": false
    },
    {
      "id": 209751,
      "adult": false
    },
    {
      "id": 133670,
      "adult": false
    },
    {
      "id": 139628,
      "adult": false
    },
    {
      "id": 72748,
      "adult": false
    },
    {
      "id": 137043,
      "adult": false
    },
    {
      "id": 216422,
      "adult": false
    },
    {
      "id": 156218,
      "adult": false
    },
    {
      "id": 93705,
      "adult": false
    },
    {
      "id": 17335,
      "adult": false
    },
    {
      "id": 212963,
      "adult": false
    },
    {
      "id": 156051,
      "adult": false
    },
    {
      "id": 214986,
      "adult": false
    },
    {
      "id": 74415,
      "adult": false
    },
    {
      "id": 118179,
      "adult": true
    },
    {
      "id": 216414,
      "adult": null
    },
    {
      "id": 130542,
      "adult": false
    },
    {
      "id": 132944,
      "adult": false
    },
    {
      "id": 98123,
      "adult": false
    },
    {
      "id": 6297,
      "adult": false
    },
    {
      "id": 2048,
      "adult": false
    },
    {
      "id": 268,
      "adult": false
    },
    {
      "id": 100466,
      "adult": false
    },
    {
      "id": 118781,
      "adult": false
    },
    {
      "id": 156868,
      "adult": false
    },
    {
      "id": 100088,
      "adult": false
    },
    {
      "id": 155857,
      "adult": false
    },
    {
      "id": 2051,
      "adult": false
    },
    {
      "id": 216260,
      "adult": false
    },
    {
      "id": 95403,
      "adult": false
    },
    {
      "id": 158017,
      "adult": false
    },
    {
      "id": 215728,
      "adult": false
    },
    {
      "id": 89638,
      "adult": false
    },
    {
      "id": 82883,
      "adult": false
    },
    {
      "id": 114452,
      "adult": true
    },
    {
      "id": 69459,
      "adult": false
    },
    {
      "id": 35524,
      "adult": false
    },
    {
      "id": 72311,
      "adult": false
    },
    {
      "id": 32788,
      "adult": false
    },
    {
      "id": 216397,
      "adult": false
    },
    {
      "id": 216352,
      "adult": false
    },
    {
      "id": 69420,
      "adult": false
    },
    {
      "id": 215069,
      "adult": false
    },
    {
      "id": 197679,
      "adult": false
    },
    {
      "id": 70941,
      "adult": false
    },
    {
      "id": 157459,
      "adult": false
    },
    {
      "id": 89180,
      "adult": false
    },
    {
      "id": 88567,
      "adult": false
    },
    {
      "id": 154725,
      "adult": false
    },
    {
      "id": 67075,
      "adult": false
    },
    {
      "id": 71915,
      "adult": false
    },
    {
      "id": 2585,
      "adult": false
    },
    {
      "id": 216163,
      "adult": false
    },
    {
      "id": 216220,
      "adult": false
    },
    {
      "id": 65334,
      "adult": false
    },
    {
      "id": 203822,
      "adult": false
    },
    {
      "id": 133490,
      "adult": false
    },
    {
      "id": 106399,
      "adult": false
    },
    {
      "id": 216401,
      "adult": false
    },
    {
      "id": 43631,
      "adult": false
    },
    {
      "id": 70485,
      "adult": false
    },
    {
      "id": 216421,
      "adult": false
    },
    {
      "id": 127633,
      "adult": false
    },
    {
      "id": 83936,
      "adult": false
    },
    {
      "id": 209321,
      "adult": false
    },
    {
      "id": 86340,
      "adult": false
    },
    {
      "id": 133153,
      "adult": false
    },
    {
      "id": 118460,
      "adult": false
    },
    {
      "id": 112696,
      "adult": false
    },
    {
      "id": 11245,
      "adult": false
    },
    {
      "id": 97970,
      "adult": false
    },
    {
      "id": 211057,
      "adult": false
    },
    {
      "id": 32896,
      "adult": false
    },
    {
      "id": 206709,
      "adult": false
    },
    {
      "id": 126198,
      "adult": true
    },
    {
      "id": 196732,
      "adult": false
    },
    {
      "id": 204716,
      "adult": false
    },
    {
      "id": 216095,
      "adult": false
    },
    {
      "id": 216016,
      "adult": null
    },
    {
      "id": 209654,
      "adult": false
    },
    {
      "id": 105511,
      "adult": false
    },
    {
      "id": 76713,
      "adult": false
    },
    {
      "id": 132145,
      "adult": false
    },
    {
      "id": 10926,
      "adult": false
    },
    {
      "id": 83251,
      "adult": false
    },
    {
      "id": 216350,
      "adult": false
    },
    {
      "id": 63161,
      "adult": false
    },
    {
      "id": 63767,
      "adult": false
    },
    {
      "id": 121750,
      "adult": false
    },
    {
      "id": 2557,
      "adult": false
    },
    {
      "id": 157377,
      "adult": false
    },
    {
      "id": 155898,
      "adult": false
    },
    {
      "id": 212536,
      "adult": true
    },
    {
      "id": 96565,
      "adult": false
    },
    {
      "id": 209652,
      "adult": false
    },
    {
      "id": 63152,
      "adult": false
    },
    {
      "id": 97575,
      "adult": true
    },
    {
      "id": 98566,
      "adult": false
    },
    {
      "id": 112314,
      "adult": false
    },
    {
      "id": 33101,
      "adult": false
    },
    {
      "id": 207889,
      "adult": false
    },
    {
      "id": 102455,
      "adult": false
    },
    {
      "id": 203599,
      "adult": false
    },
    {
      "id": 216426,
      "adult": false
    },
    {
      "id": 82089,
      "adult": false
    },
    {
      "id": 103759,
      "adult": false
    },
    {
      "id": 215157,
      "adult": false
    },
    {
      "id": 513,
      "adult": false
    },
    {
      "id": 82585,
      "adult": false
    },
    {
      "id": 158347,
      "adult": false
    },
    {
      "id": 153312,
      "adult": false
    },
    {
      "id": 197078,
      "adult": false
    },
    {
      "id": 209247,
      "adult": false
    },
    {
      "id": 138971,
      "adult": false
    },
    {
      "id": 137575,
      "adult": false
    },
    {
      "id": 99966,
      "adult": false
    },
    {
      "id": 215455,
      "adult": false
    },
    {
      "id": 208195,
      "adult": false
    },
    {
      "id": 205856,
      "adult": false
    },
    {
      "id": 90712,
      "adult": false
    },
    {
      "id": 212720,
      "adult": null
    },
    {
      "id": 120470,
      "adult": false
    },
    {
      "id": 119985,
      "adult": false
    },
    {
      "id": 25507,
      "adult": false
    },
    {
      "id": 43951,
      "adult": false
    },
    {
      "id": 84969,
      "adult": false
    },
    {
      "id": 137437,
      "adult": false
    },
    {
      "id": 135355,
      "adult": false
    },
    {
      "id": 215384,
      "adult": false
    },
    {
      "id": 155459,
      "adult": false
    },
    {
      "id": 95396,
      "adult": false
    },
    {
      "id": 214949,
      "adult": false
    },
    {
      "id": 205137,
      "adult": false
    },
    {
      "id": 76054,
      "adult": false
    },
    {
      "id": 215596,
      "adult": true
    },
    {
      "id": 216127,
      "adult": false
    },
    {
      "id": 28061,
      "adult": false
    },
    {
      "id": 1415,
      "adult": false
    },
    {
      "id": 64448,
      "adult": false
    },
    {
      "id": 46387,
      "adult": false
    },
    {
      "id": 86189,
      "adult": false
    },
    {
      "id": 129020,
      "adult": false
    },
    {
      "id": 196400,
      "adult": false
    },
    {
      "id": 68250,
      "adult": false
    },
    {
      "id": 40424,
      "adult": false
    },
    {
      "id": 197072,
      "adult": false
    },
    {
      "id": 105971,
      "adult": false
    },
    {
      "id": 76949,
      "adult": false
    },
    {
      "id": 126203,
      "adult": true
    },
    {
      "id": 62560,
      "adult": false
    },
    {
      "id": 157064,
      "adult": false
    },
    {
      "id": 2190,
      "adult": false
    },
    {
      "id": 99346,
      "adult": false
    },
    {
      "id": 33342,
      "adult": false
    },
    {
      "id": 207020,
      "adult": false
    },
    {
      "id": 97617,
      "adult": false
    },
    {
      "id": 76141,
      "adult": false
    },
    {
      "id": 214686,
      "adult": false
    },
    {
      "id": 204254,
      "adult": false
    },
    {
      "id": 78672,
      "adult": false
    },
    {
      "id": 65628,
      "adult": false
    },
    {
      "id": 46881,
      "adult": false
    },
    {
      "id": 216423,
      "adult": false
    },
    {
      "id": 211841,
      "adult": false
    },
    {
      "id": 12786,
      "adult": false
    },
    {
      "id": 77994,
      "adult": false
    },
    {
      "id": 215492,
      "adult": false
    },
    {
      "id": 201841,
      "adult": false
    },
    {
      "id": 214483,
      "adult": false
    },
    {
      "id": 73395,
      "adult": false
    },
    {
      "id": 34634,
      "adult": false
    },
    {
      "id": 162,
      "adult": false
    },
    {
      "id": 206013,
      "adult": false
    },
    {
      "id": 139676,
      "adult": false
    },
    {
      "id": 26732,
      "adult": false
    },
    {
      "id": 133733,
      "adult": false
    },
    {
      "id": 86256,
      "adult": false
    },
    {
      "id": 157851,
      "adult": false
    },
    {
      "id": 31718,
      "adult": false
    },
    {
      "id": 14929,
      "adult": false
    },
    {
      "id": 126254,
      "adult": false
    },
    {
      "id": 63639,
      "adult": false
    },
    {
      "id": 214450,
      "adult": false
    },
    {
      "id": 60210,
      "adult": false
    },
    {
      "id": 35338,
      "adult": false
    },
    {
      "id": 70508,
      "adult": false
    },
    {
      "id": 98251,
      "adult": false
    },
    {
      "id": 54933,
      "adult": false
    },
    {
      "id": 216379,
      "adult": false
    },
    {
      "id": 39959,
      "adult": false
    },
    {
      "id": 2199,
      "adult": false
    },
    {
      "id": 5273,
      "adult": false
    },
    {
      "id": 96777,
      "adult": false
    },
    {
      "id": 135155,
      "adult": false
    },
    {
      "id": 2734,
      "adult": false
    },
    {
      "id": 214520,
      "adult": false
    },
    {
      "id": 216195,
      "adult": false
    },
    {
      "id": 71027,
      "adult": false
    },
    {
      "id": 210768,
      "adult": false
    },
    {
      "id": 210701,
      "adult": false
    },
    {
      "id": 119033,
      "adult": false
    },
    {
      "id": 16324,
      "adult": false
    },
    {
      "id": 60381,
      "adult": false
    },
    {
      "id": 93808,
      "adult": false
    },
    {
      "id": 207669,
      "adult": false
    },
    {
      "id": 47987,
      "adult": false
    },
    {
      "id": 34891,
      "adult": false
    },
    {
      "id": 202307,
      "adult": false
    },
    {
      "id": 10779,
      "adult": false
    },
    {
      "id": 46129,
      "adult": false
    },
    {
      "id": 62481,
      "adult": false
    },
    {
      "id": 205636,
      "adult": false
    },
    {
      "id": 40663,
      "adult": false
    },
    {
      "id": 153588,
      "adult": false
    },
    {
      "id": 216355,
      "adult": false
    },
    {
      "id": 95,
      "adult": false
    },
    {
      "id": 213044,
      "adult": false
    },
    {
      "id": 107124,
      "adult": false
    },
    {
      "id": 129195,
      "adult": false
    },
    {
      "id": 216313,
      "adult": false
    },
    {
      "id": 3934,
      "adult": false
    },
    {
      "id": 73586,
      "adult": false
    },
    {
      "id": 21855,
      "adult": false
    },
    {
      "id": 210955,
      "adult": false
    },
    {
      "id": 97038,
      "adult": true
    },
    {
      "id": 50237,
      "adult": false
    },
    {
      "id": 204589,
      "adult": false
    },
    {
      "id": 110119,
      "adult": false
    },
    {
      "id": 63246,
      "adult": false
    },
    {
      "id": 112792,
      "adult": false
    },
    {
      "id": 209801,
      "adult": false
    },
    {
      "id": 9161,
      "adult": false
    },
    {
      "id": 207493,
      "adult": false
    },
    {
      "id": 67584,
      "adult": false
    },
    {
      "id": 153697,
      "adult": false
    },
    {
      "id": 3312,
      "adult": false
    },
    {
      "id": 64663,
      "adult": false
    },
    {
      "id": 209708,
      "adult": false
    },
    {
      "id": 216411,
      "adult": false
    },
    {
      "id": 63119,
      "adult": false
    },
    {
      "id": 2122,
      "adult": false
    },
    {
      "id": 112791,
      "adult": false
    },
    {
      "id": 62223,
      "adult": false
    },
    {
      "id": 39351,
      "adult": false
    },
    {
      "id": 89666,
      "adult": false
    },
    {
      "id": 16316,
      "adult": false
    },
    {
      "id": 84382,
      "adult": false
    },
    {
      "id": 215624,
      "adult": false
    },
    {
      "id": 95913,
      "adult": false
    },
    {
      "id": 214969,
      "adult": false
    },
    {
      "id": 456,
      "adult": false
    },
    {
      "id": 153482,
      "adult": false
    },
    {
      "id": 92749,
      "adult": false
    },
    {
      "id": 46627,
      "adult": false
    },
    {
      "id": 110232,
      "adult": false
    },
    {
      "id": 132661,
      "adult": false
    },
    {
      "id": 134373,
      "adult": false
    },
    {
      "id": 12225,
      "adult": false
    },
    {
      "id": 63926,
      "adult": false
    },
    {
      "id": 216344,
      "adult": false
    },
    {
      "id": 71024,
      "adult": false
    },
    {
      "id": 92621,
      "adult": false
    },
    {
      "id": 24950,
      "adult": false
    },
    {
      "id": 12620,
      "adult": false
    },
    {
      "id": 3228,
      "adult": false
    },
    {
      "id": 62104,
      "adult": false
    },
    {
      "id": 106158,
      "adult": false
    },
    {
      "id": 203697,
      "adult": false
    },
    {
      "id": 200709,
      "adult": false
    },
    {
      "id": 200969,
      "adult": false
    },
    {
      "id": 208832,
      "adult": false
    },
    {
      "id": 216277,
      "adult": false
    },
    {
      "id": 75893,
      "adult": false
    },
    {
      "id": 62211,
      "adult": false
    },
    {
      "id": 83612,
      "adult": false
    },
    {
      "id": 126794,
      "adult": false
    },
    {
      "id": 64478,
      "adult": false
    },
    {
      "id": 88450,
      "adult": false
    },
    {
      "id": 59617,
      "adult": false
    },
    {
      "id": 128802,
      "adult": true
    },
    {
      "id": 62715,
      "adult": false
    },
    {
      "id": 125521,
      "adult": false
    },
    {
      "id": 117442,
      "adult": false
    },
    {
      "id": 79888,
      "adult": false
    },
    {
      "id": 135884,
      "adult": false
    },
    {
      "id": 38852,
      "adult": false
    },
    {
      "id": 202905,
      "adult": false
    },
    {
      "id": 215556,
      "adult": false
    },
    {
      "id": 216202,
      "adult": false
    },
    {
      "id": 205748,
      "adult": false
    },
    {
      "id": 65264,
      "adult": false
    },
    {
      "id": 157936,
      "adult": false
    },
    {
      "id": 93653,
      "adult": false
    },
    {
      "id": 1434,
      "adult": false
    },
    {
      "id": 95480,
      "adult": false
    },
    {
      "id": 4775,
      "adult": false
    },
    {
      "id": 105903,
      "adult": false
    },
    {
      "id": 31159,
      "adult": false
    },
    {
      "id": 7998,
      "adult": false
    },
    {
      "id": 13815,
      "adult": false
    },
    {
      "id": 214264,
      "adult": false
    },
    {
      "id": 213655,
      "adult": false
    },
    {
      "id": 75219,
      "adult": false
    },
    {
      "id": 216395,
      "adult": true
    },
    {
      "id": 97083,
      "adult": false
    },
    {
      "id": 80732,
      "adult": false
    },
    {
      "id": 71026,
      "adult": false
    },
    {
      "id": 153282,
      "adult": false
    },
    {
      "id": 2595,
      "adult": false
    },
    {
      "id": 62602,
      "adult": false
    },
    {
      "id": 8864,
      "adult": false
    },
    {
      "id": 21510,
      "adult": false
    },
    {
      "id": 16614,
      "adult": false
    },
    {
      "id": 216088,
      "adult": false
    },
    {
      "id": 215912,
      "adult": false
    },
    {
      "id": 152310,
      "adult": false
    },
    {
      "id": 113178,
      "adult": false
    },
    {
      "id": 1871,
      "adult": false
    },
    {
      "id": 211833,
      "adult": false
    },
    {
      "id": 89630,
      "adult": false
    },
    {
      "id": 79252,
      "adult": false
    },
    {
      "id": 63929,
      "adult": false
    },
    {
      "id": 14141,
      "adult": false
    },
    {
      "id": 1818,
      "adult": false
    },
    {
      "id": 81854,
      "adult": false
    },
    {
      "id": 62328,
      "adult": false
    },
    {
      "id": 207468,
      "adult": false
    },
    {
      "id": 216432,
      "adult": false
    },
    {
      "id": 76075,
      "adult": false
    },
    {
      "id": 52891,
      "adult": false
    },
    {
      "id": 109804,
      "adult": false
    },
    {
      "id": 109350,
      "adult": true
    },
    {
      "id": 154359,
      "adult": false
    },
    {
      "id": 13916,
      "adult": false
    },
    {
      "id": 125714,
      "adult": false
    },
    {
      "id": 58955,
      "adult": false
    },
    {
      "id": 110381,
      "adult": false
    },
    {
      "id": 72136,
      "adult": false
    },
    {
      "id": 1938,
      "adult": false
    },
    {
      "id": 101359,
      "adult": false
    },
    {
      "id": 52114,
      "adult": false
    },
    {
      "id": 68507,
      "adult": false
    },
    {
      "id": 14976,
      "adult": false
    },
    {
      "id": 63714,
      "adult": false
    },
    {
      "id": 99616,
      "adult": false
    },
    {
      "id": 122725,
      "adult": false
    },
    {
      "id": 106393,
      "adult": false
    },
    {
      "id": 215022,
      "adult": false
    },
    {
      "id": 87386,
      "adult": false
    },
    {
      "id": 195990,
      "adult": false
    },
    {
      "id": 123473,
      "adult": false
    },
    {
      "id": 152474,
      "adult": false
    },
    {
      "id": 83125,
      "adult": false
    },
    {
      "id": 213083,
      "adult": false
    },
    {
      "id": 152461,
      "adult": false
    },
    {
      "id": 108467,
      "adult": false
    },
    {
      "id": 119773,
      "adult": false
    },
    {
      "id": 205223,
      "adult": false
    },
    {
      "id": 206510,
      "adult": false
    },
    {
      "id": 61221,
      "adult": false
    },
    {
      "id": 34071,
      "adult": false
    },
    {
      "id": 24769,
      "adult": false
    },
    {
      "id": 216170,
      "adult": false
    },
    {
      "id": 83321,
      "adult": false
    },
    {
      "id": 82596,
      "adult": false
    },
    {
      "id": 208751,
      "adult": false
    },
    {
      "id": 110531,
      "adult": false
    },
    {
      "id": 66272,
      "adult": false
    },
    {
      "id": 215092,
      "adult": false
    },
    {
      "id": 45954,
      "adult": false
    },
    {
      "id": 93870,
      "adult": false
    },
    {
      "id": 91502,
      "adult": false
    },
    {
      "id": 39273,
      "adult": false
    },
    {
      "id": 101626,
      "adult": false
    },
    {
      "id": 122012,
      "adult": false
    },
    {
      "id": 21936,
      "adult": false
    },
    {
      "id": 45666,
      "adult": false
    },
    {
      "id": 74018,
      "adult": false
    },
    {
      "id": 3731,
      "adult": false
    },
    {
      "id": 72649,
      "adult": false
    },
    {
      "id": 135622,
      "adult": false
    },
    {
      "id": 136857,
      "adult": false
    },
    {
      "id": 117166,
      "adult": false
    },
    {
      "id": 68388,
      "adult": false
    },
    {
      "id": 215947,
      "adult": false
    },
    {
      "id": 6956,
      "adult": false
    },
    {
      "id": 14317,
      "adult": false
    },
    {
      "id": 112945,
      "adult": false
    },
    {
      "id": 126123,
      "adult": false
    },
    {
      "id": 25492,
      "adult": false
    },
    {
      "id": 96882,
      "adult": false
    },
    {
      "id": 98213,
      "adult": false
    },
    {
      "id": 203949,
      "adult": false
    },
    {
      "id": 214663,
      "adult": false
    },
    {
      "id": 207863,
      "adult": false
    },
    {
      "id": 128033,
      "adult": false
    },
    {
      "id": 209217,
      "adult": false
    },
    {
      "id": 156092,
      "adult": false
    },
    {
      "id": 120822,
      "adult": true
    },
    {
      "id": 127714,
      "adult": false
    },
    {
      "id": 115477,
      "adult": false
    },
    {
      "id": 194736,
      "adult": false
    },
    {
      "id": 216429,
      "adult": false
    },
    {
      "id": 202648,
      "adult": false
    },
    {
      "id": 40971,
      "adult": false
    },
    {
      "id": 158373,
      "adult": false
    },
    {
      "id": 204749,
      "adult": false
    },
    {
      "id": 94600,
      "adult": false
    },
    {
      "id": 63164,
      "adult": false
    },
    {
      "id": 41698,
      "adult": false
    },
    {
      "id": 204736,
      "adult": false
    },
    {
      "id": 137518,
      "adult": false
    },
    {
      "id": 210532,
      "adult": false
    },
    {
      "id": 81354,
      "adult": false
    },
    {
      "id": 215221,
      "adult": true
    },
    {
      "id": 105962,
      "adult": false
    },
    {
      "id": 198152,
      "adult": false
    },
    {
      "id": 216304,
      "adult": false
    },
    {
      "id": 111998,
      "adult": false
    },
    {
      "id": 42339,
      "adult": false
    },
    {
      "id": 120573,
      "adult": false
    },
    {
      "id": 216402,
      "adult": false
    },
    {
      "id": 214956,
      "adult": false
    },
    {
      "id": 133938,
      "adult": false
    },
    {
      "id": 42722,
      "adult": false
    },
    {
      "id": 47907,
      "adult": false
    },
    {
      "id": 200777,
      "adult": false
    },
    {
      "id": 99256,
      "adult": false
    },
    {
      "id": 45967,
      "adult": false
    },
    {
      "id": 128098,
      "adult": false
    },
    {
      "id": 95439,
      "adult": false
    },
    {
      "id": 97929,
      "adult": true
    },
    {
      "id": 111838,
      "adult": false
    },
    {
      "id": 83118,
      "adult": false
    },
    {
      "id": 216241,
      "adult": false
    },
    {
      "id": 60625,
      "adult": false
    },
    {
      "id": 157744,
      "adult": false
    },
    {
      "id": 20941,
      "adult": false
    },
    {
      "id": 41211,
      "adult": false
    },
    {
      "id": 119694,
      "adult": false
    },
    {
      "id": 37305,
      "adult": false
    },
    {
      "id": 216425,
      "adult": false
    },
    {
      "id": 75132,
      "adult": false
    },
    {
      "id": 122902,
      "adult": false
    },
    {
      "id": 196965,
      "adult": false
    },
    {
      "id": 82856,
      "adult": false
    },
    {
      "id": 197073,
      "adult": false
    },
    {
      "id": 155468,
      "adult": false
    },
    {
      "id": 206625,
      "adult": false
    },
    {
      "id": 90151,
      "adult": true
    },
    {
      "id": 211163,
      "adult": false
    },
    {
      "id": 209350,
      "adult": false
    },
    {
      "id": 158418,
      "adult": false
    },
    {
      "id": 110873,
      "adult": false
    },
    {
      "id": 32836,
      "adult": false
    },
    {
      "id": 77548,
      "adult": false
    },
    {
      "id": 216291,
      "adult": false
    },
    {
      "id": 216393,
      "adult": false
    },
    {
      "id": 85129,
      "adult": true
    },
    {
      "id": 112405,
      "adult": false
    },
    {
      "id": 154524,
      "adult": false
    },
    {
      "id": 19077,
      "adult": false
    },
    {
      "id": 106925,
      "adult": false
    },
    {
      "id": 135775,
      "adult": false
    },
    {
      "id": 66914,
      "adult": false
    },
    {
      "id": 93288,
      "adult": false
    },
    {
      "id": 82791,
      "adult": false
    },
    {
      "id": 60554,
      "adult": false
    },
    {
      "id": 196369,
      "adult": false
    },
    {
      "id": 5080,
      "adult": false
    },
    {
      "id": 127635,
      "adult": false
    },
    {
      "id": 216036,
      "adult": false
    },
    {
      "id": 46262,
      "adult": false
    },
    {
      "id": 66240,
      "adult": false
    },
    {
      "id": 52083,
      "adult": false
    },
    {
      "id": 107130,
      "adult": false
    },
    {
      "id": 3108,
      "adult": false
    },
    {
      "id": 214406,
      "adult": false
    },
    {
      "id": 208303,
      "adult": false
    },
    {
      "id": 208691,
      "adult": false
    },
    {
      "id": 216413,
      "adult": false
    },
    {
      "id": 16299,
      "adult": false
    },
    {
      "id": 126929,
      "adult": false
    },
    {
      "id": 122747,
      "adult": false
    },
    {
      "id": 212457,
      "adult": false
    },
    {
      "id": 153818,
      "adult": false
    },
    {
      "id": 216367,
      "adult": false
    },
    {
      "id": 119495,
      "adult": false
    },
    {
      "id": 121870,
      "adult": false
    },
    {
      "id": 62742,
      "adult": false
    },
    {
      "id": 1920,
      "adult": false
    },
    {
      "id": 215629,
      "adult": false
    },
    {
      "id": 97525,
      "adult": false
    },
    {
      "id": 14396,
      "adult": false
    },
    {
      "id": 123976,
      "adult": false
    },
    {
      "id": 70639,
      "adult": false
    },
    {
      "id": 138561,
      "adult": false
    },
    {
      "id": 131369,
      "adult": false
    },
    {
      "id": 216392,
      "adult": false
    },
    {
      "id": 93657,
      "adult": false
    },
    {
      "id": 195743,
      "adult": false
    },
    {
      "id": 1781,
      "adult": false
    },
    {
      "id": 44077,
      "adult": null
    },
    {
      "id": 93716,
      "adult": false
    },
    {
      "id": 197294,
      "adult": false
    },
    {
      "id": 31586,
      "adult": false
    },
    {
      "id": 134667,
      "adult": false
    },
    {
      "id": 213274,
      "adult": false
    },
    {
      "id": 107519,
      "adult": false
    },
    {
      "id": 124415,
      "adult": false
    },
    {
      "id": 210229,
      "adult": false
    },
    {
      "id": 215768,
      "adult": false
    },
    {
      "id": 87758,
      "adult": false
    },
    {
      "id": 5582,
      "adult": false
    },
    {
      "id": 90721,
      "adult": false
    },
    {
      "id": 216351,
      "adult": false
    },
    {
      "id": 68136,
      "adult": false
    },
    {
      "id": 80748,
      "adult": false
    },
    {
      "id": 213798,
      "adult": false
    },
    {
      "id": 216396,
      "adult": false
    },
    {
      "id": 65701,
      "adult": false
    },
    {
      "id": 79093,
      "adult": false
    },
    {
      "id": 213406,
      "adult": false
    },
    {
      "id": 53916,
      "adult": false
    },
    {
      "id": 74204,
      "adult": false
    },
    {
      "id": 40157,
      "adult": false
    },
    {
      "id": 136673,
      "adult": false
    },
    {
      "id": 118956,
      "adult": false
    },
    {
      "id": 32916,
      "adult": false
    },
    {
      "id": 4699,
      "adult": false
    },
    {
      "id": 39852,
      "adult": false
    },
    {
      "id": 7637,
      "adult": false
    },
    {
      "id": 97963,
      "adult": true
    },
    {
      "id": 1404,
      "adult": false
    },
    {
      "id": 112010,
      "adult": false
    },
    {
      "id": 206878,
      "adult": false
    },
    {
      "id": 1554,
      "adult": false
    },
    {
      "id": 4521,
      "adult": false
    },
    {
      "id": 87491,
      "adult": false
    },
    {
      "id": 57532,
      "adult": false
    },
    {
      "id": 205715,
      "adult": false
    },
    {
      "id": 111837,
      "adult": false
    },
    {
      "id": 214325,
      "adult": false
    },
    {
      "id": 63692,
      "adult": false
    },
    {
      "id": 63663,
      "adult": false
    },
    {
      "id": 4238,
      "adult": false
    },
    {
      "id": 216431,
      "adult": false
    },
    {
      "id": 215766,
      "adult": false
    },
    {
      "id": 65746,
      "adult": false
    },
    {
      "id": 112470,
      "adult": false
    },
    {
      "id": 207878,
      "adult": false
    },
    {
      "id": 155889,
      "adult": false
    },
    {
      "id": 214619,
      "adult": false
    },
    {
      "id": 91426,
      "adult": false
    },
    {
      "id": 133805,
      "adult": true
    },
    {
      "id": 112836,
      "adult": false
    },
    {
      "id": 206748,
      "adult": false
    },
    {
      "id": 155631,
      "adult": false
    },
    {
      "id": 210542,
      "adult": false
    },
    {
      "id": 204129,
      "adult": false
    },
    {
      "id": 203192,
      "adult": false
    },
    {
      "id": 1413,
      "adult": false
    },
    {
      "id": 213567,
      "adult": false
    },
    {
      "id": 4057,
      "adult": false
    },
    {
      "id": 44606,
      "adult": false
    },
    {
      "id": 138289,
      "adult": false
    },
    {
      "id": 215902,
      "adult": false
    },
    {
      "id": 195921,
      "adult": false
    },
    {
      "id": 155372,
      "adult": false
    },
    {
      "id": 57757,
      "adult": false
    },
    {
      "id": 196526,
      "adult": false
    },
    {
      "id": 205961,
      "adult": false
    },
    {
      "id": 156053,
      "adult": false
    },
    {
      "id": 100191,
      "adult": false
    },
    {
      "id": 97878,
      "adult": false
    },
    {
      "id": 127588,
      "adult": false
    },
    {
      "id": 62702,
      "adult": false
    },
    {
      "id": 208677,
      "adult": false
    },
    {
      "id": 216419,
      "adult": false
    },
    {
      "id": 216369,
      "adult": false
    },
    {
      "id": 216420,
      "adult": false
    },
    {
      "id": 3287,
      "adult": false
    },
    {
      "id": 216245,
      "adult": false
    },
    {
      "id": 67977,
      "adult": false
    },
    {
      "id": 201331,
      "adult": false
    },
    {
      "id": 216391,
      "adult": false
    },
    {
      "id": 210708,
      "adult": false
    },
    {
      "id": 110317,
      "adult": false
    },
    {
      "id": 216214,
      "adult": false
    },
    {
      "id": 88189,
      "adult": false
    },
    {
      "id": 216359,
      "adult": false
    },
    {
      "id": 102085,
      "adult": false
    },
    {
      "id": 210195,
      "adult": false
    },
    {
      "id": 73394,
      "adult": false
    },
    {
      "id": 216409,
      "adult": false
    },
    {
      "id": 38812,
      "adult": false
    },
    {
      "id": 75431,
      "adult": false
    },
    {
      "id": 95213,
      "adult": false
    },
    {
      "id": 61550,
      "adult": false
    },
    {
      "id": 4164,
      "adult": false
    },
    {
      "id": 1750,
      "adult": false
    },
    {
      "id": 99440,
      "adult": false
    },
    {
      "id": 205594,
      "adult": false
    },
    {
      "id": 154677,
      "adult": false
    },
    {
      "id": 105869,
      "adult": false
    },
    {
      "id": 87917,
      "adult": false
    },
    {
      "id": 56355,
      "adult": false
    },
    {
      "id": 202250,
      "adult": false
    },
    {
      "id": 108284,
      "adult": false
    },
    {
      "id": 104359,
      "adult": false
    },
    {
      "id": 33347,
      "adult": false
    },
    {
      "id": 157437,
      "adult": false
    },
    {
      "id": 216415,
      "adult": false
    },
    {
      "id": 139004,
      "adult": false
    },
    {
      "id": 56498,
      "adult": false
    },
    {
      "id": 197979,
      "adult": false
    },
    {
      "id": 78107,
      "adult": false
    },
    {
      "id": 76132,
      "adult": false
    },
    {
      "id": 66025,
      "adult": false
    },
    {
      "id": 85937,
      "adult": false
    },
    {
      "id": 23589,
      "adult": false
    },
    {
      "id": 216412,
      "adult": false
    },
    {
      "id": 1639,
      "adult": false
    },
    {
      "id": 62849,
      "adult": false
    },
    {
      "id": 88662,
      "adult": false
    },
    {
      "id": 130020,
      "adult": false
    },
    {
      "id": 137216,
      "adult": false
    },
    {
      "id": 64487,
      "adult": false
    },
    {
      "id": 215878,
      "adult": false
    },
    {
      "id": 216410,
      "adult": false
    },
    {
      "id": 14506,
      "adult": false
    },
    {
      "id": 202974,
      "adult": false
    },
    {
      "id": 203741,
      "adult": false
    },
    {
      "id": 118663,
      "adult": false
    },
    {
      "id": 215091,
      "adult": false
    },
    {
      "id": 201083,
      "adult": false
    },
    {
      "id": 123125,
      "adult": false
    },
    {
      "id": 126209,
      "adult": false
    },
    {
      "id": 3218,
      "adult": false
    },
    {
      "id": 210889,
      "adult": false
    },
    {
      "id": 28184,
      "adult": false
    },
    {
      "id": 51806,
      "adult": false
    },
    {
      "id": 211174,
      "adult": false
    },
    {
      "id": 156510,
      "adult": false
    },
    {
      "id": 42671,
      "adult": false
    },
    {
      "id": 62102,
      "adult": false
    },
    {
      "id": 216407,
      "adult": false
    },
    {
      "id": 208925,
      "adult": false
    },
    {
      "id": 97611,
      "adult": true
    },
    {
      "id": 203698,
      "adult": false
    },
    {
      "id": 203554,
      "adult": false
    },
    {
      "id": 123999,
      "adult": false
    },
    {
      "id": 210020,
      "adult": false
    },
    {
      "id": 80279,
      "adult": false
    },
    {
      "id": 82104,
      "adult": false
    },
    {
      "id": 79744,
      "adult": false
    },
    {
      "id": 208570,
      "adult": false
    },
    {
      "id": 64550,
      "adult": false
    },
    {
      "id": 12663,
      "adult": false
    },
    {
      "id": 216416,
      "adult": false
    },
    {
      "id": 195039,
      "adult": false
    },
    {
      "id": 790,
      "adult": false
    },
    {
      "id": 216417,
      "adult": false
    },
    {
      "id": 4194,
      "adult": false
    },
    {
      "id": 78122,
      "adult": false
    },
    {
      "id": 75865,
      "adult": false
    },
    {
      "id": 216405,
      "adult": false
    },
    {
      "id": 100833,
      "adult": false
    },
    {
      "id": 214124,
      "adult": false
    },
    {
      "id": 210916,
      "adult": false
    },
    {
      "id": 82448,
      "adult": false
    },
    {
      "id": 97890,
      "adult": false
    },
    {
      "id": 120591,
      "adult": false
    },
    {
      "id": 111453,
      "adult": false
    },
    {
      "id": 111204,
      "adult": false
    },
    {
      "id": 65076,
      "adult": false
    },
    {
      "id": 113267,
      "adult": false
    },
    {
      "id": 136283,
      "adult": false
    },
    {
      "id": 113966,
      "adult": false
    },
    {
      "id": 106116,
      "adult": false
    },
    {
      "id": 91801,
      "adult": false
    },
    {
      "id": 209504,
      "adult": false
    },
    {
      "id": 47663,
      "adult": false
    },
    {
      "id": 63181,
      "adult": false
    },
    {
      "id": 215117,
      "adult": false
    },
    {
      "id": 113444,
      "adult": false
    },
    {
      "id": 210444,
      "adult": false
    },
    {
      "id": 209918,
      "adult": false
    },
    {
      "id": 2912,
      "adult": false
    },
    {
      "id": 215330,
      "adult": false
    },
    {
      "id": 46412,
      "adult": false
    },
    {
      "id": 216353,
      "adult": false
    },
    {
      "id": 48720,
      "adult": false
    },
    {
      "id": 208336,
      "adult": false
    },
    {
      "id": 154820,
      "adult": false
    },
    {
      "id": 202017,
      "adult": false
    },
    {
      "id": 158206,
      "adult": true
    },
    {
      "id": 215874,
      "adult": false
    },
    {
      "id": 93014,
      "adult": false
    },
    {
      "id": 78081,
      "adult": false
    },
    {
      "id": 156052,
      "adult": false
    },
    {
      "id": 92911,
      "adult": false
    },
    {
      "id": 216406,
      "adult": null
    },
    {
      "id": 94951,
      "adult": false
    },
    {
      "id": 83867,
      "adult": false
    },
    {
      "id": 216062,
      "adult": false
    },
    {
      "id": 103254,
      "adult": false
    },
    {
      "id": 204070,
      "adult": false
    },
    {
      "id": 76345,
      "adult": false
    },
    {
      "id": 93655,
      "adult": false
    },
    {
      "id": 17149,
      "adult": false
    },
    {
      "id": 34791,
      "adult": false
    },
    {
      "id": 215727,
      "adult": false
    },
    {
      "id": 125118,
      "adult": false
    },
    {
      "id": 31991,
      "adult": false
    },
    {
      "id": 115194,
      "adult": false
    },
    {
      "id": 135934,
      "adult": false
    },
    {
      "id": 153445,
      "adult": false
    },
    {
      "id": 1789,
      "adult": false
    },
    {
      "id": 33976,
      "adult": false
    },
    {
      "id": 3772,
      "adult": false
    },
    {
      "id": 201478,
      "adult": false
    },
    {
      "id": 732,
      "adult": false
    },
    {
      "id": 3122,
      "adult": false
    },
    {
      "id": 129418,
      "adult": false
    },
    {
      "id": 110948,
      "adult": false
    }
  ],
  "page": 1,
  "total_pages": 1,
  "total_results": 1
}
